rolld/__init__.py
rolld/_types.py
rolld/roll.py
pyrolld-0.2.2.dist-info/WHEEL
pyrolld-0.2.2.dist-info/METADATA
pyrolld-0.2.2.dist-info/RECORD
