Metadata-Version: 2.1
Name: pyrolld
Version: 0.2.2
Summary: A package to generate color sequences from videos and images
License: MIT
Author: Vitaman02
Requires-Python: >=3.8.1,<4.0.0
Classifier: License :: OSI Approved :: MIT License
Classifier: Programming Language :: Python :: 3
Classifier: Programming Language :: Python :: 3.9
Classifier: Programming Language :: Python :: 3.10
Classifier: Programming Language :: Python :: 3.11
Requires-Dist: pillow (>=9.0,<10.0)
Requires-Dist: types-pillow (>=9.0,<10.0)
